unofficial_tabdeal_api/__init__.py
unofficial_tabdeal_api/authorization.py
unofficial_tabdeal_api/base.py
unofficial_tabdeal_api/constants.py
unofficial_tabdeal_api/enums.py
unofficial_tabdeal_api/exceptions.py
unofficial_tabdeal_api/margin.py
unofficial_tabdeal_api/models.py
unofficial_tabdeal_api/order.py
unofficial_tabdeal_api/py.typed
unofficial_tabdeal_api/tabdeal_client.py
unofficial_tabdeal_api/utils.py
unofficial_tabdeal_api/wallet.py
unofficial_tabdeal_api-0.3.9.dist-info/LICENSE
unofficial_tabdeal_api-0.3.9.dist-info/METADATA
unofficial_tabdeal_api-0.3.9.dist-info/WHEEL
unofficial_tabdeal_api-0.3.9.dist-info/RECORD
