Metadata-Version: 2.3
Name: unofficial_tabdeal_api
Version: 0.3.9
Summary: A Package to communicate with the Tabdeal platform
License: MIT
Keywords: tabdeal,api,unofficial
Author: MohsenHNSJ
Author-email: mohsenhasannezhad@outlook.com
Maintainer: MohsenHNSJ
Maintainer-email: mohsenhasannezhad@outlook.com
Requires-Python: >=3.11
Classifier: Framework :: aiohttp
Classifier: Framework :: AsyncIO
Classifier: Framework :: Pydantic :: 2
Classifier: Topic :: Internet :: WWW/HTTP :: Session
Classifier: Topic :: Office/Business :: Financial :: Investment
Classifier: Topic :: Software Development :: Libraries :: Python Modules
Classifier: Development Status :: 4 - Beta
Classifier: License :: OSI Approved :: MIT License
Classifier: Programming Language :: Python :: 3.11
Classifier: Programming Language :: Python :: 3.12
Classifier: Programming Language :: Python :: 3.13
Classifier: Operating System :: OS Independent
Classifier: Intended Audience :: Developers
Classifier: Intended Audience :: End Users/Desktop
Classifier: Intended Audience :: Financial and Insurance Industry
Classifier: Natural Language :: English
Classifier: Typing :: Typed
Requires-Dist: aiohttp (==3.12.14)
Requires-Dist: pydantic (==2.9.2)
Project-URL: Bug, https://github.com/MohsenHNSJ/unofficial_tabdeal_api/issues
Project-URL: Changelog, https://github.com/MohsenHNSJ/unofficial_tabdeal_api/releases
Project-URL: Documentation, https://unofficial-tabdeal-api.readthedocs.io/en/latest/
Project-URL: Repository, https://github.com/MohsenHNSJ/unofficial_tabdeal_api
